examples/cloud_function_client_example.py
examples/dead_letter_handler.py
examples/full_featured_agent.py
examples/oss_test.py
examples/quickstart_agent.py
examples/test_robot_registration.py
uni_agent_sdk/__init__.py
uni_agent_sdk/agent.py
uni_agent_sdk/build_system/__init__.py
uni_agent_sdk/build_system/build_manager.py
uni_agent_sdk/build_system/cloud_function_client.py
uni_agent_sdk/build_system/config_provider.py
uni_agent_sdk/build_system/docker_client.py
uni_agent_sdk/build_system/dockerfile_generator.py
uni_agent_sdk/build_system/publish_manager.py
uni_agent_sdk/build_system/run_manager.py
uni_agent_sdk/cli/__init__.py
uni_agent_sdk/cli/__main__.py
uni_agent_sdk/cli/app.py
uni_agent_sdk/cli/build.py
uni_agent_sdk/cli/commands.py
uni_agent_sdk/cli/publish.py
uni_agent_sdk/cli/scaffold.py
uni_agent_sdk/core/__init__.py
uni_agent_sdk/core/context.py
uni_agent_sdk/core/lifecycle.py
uni_agent_sdk/core/message_broker.py
uni_agent_sdk/models/__init__.py
uni_agent_sdk/models/message.py
uni_agent_sdk/services/__init__.py
uni_agent_sdk/services/file.py
uni_agent_sdk/services/llm.py
uni_agent_sdk/services/platform.py
uni_agent_sdk/utils/__init__.py
uni_agent_sdk/utils/config.py
uni_agent_sdk/utils/crypto.py
uni_agent_sdk/utils/errors.py
uni_agent_sdk/utils/logger.py
uni_agent_sdk-0.2.4.dist-info/METADATA
uni_agent_sdk-0.2.4.dist-info/WHEEL
uni_agent_sdk-0.2.4.dist-info/entry_points.txt
uni_agent_sdk-0.2.4.dist-info/top_level.txt
uni_agent_sdk-0.2.4.dist-info/RECORD
