Metadata-Version: 2.4
Name: uni_agent_sdk
Version: 0.2.4
Summary: 极简的uni-im平台智能体开发框架
Home-page: https://github.com/uni-im/uni-agent-sdk
Author: uni-im
Author-email: uni-im <support@uni-im.com>
Maintainer-email: uni-im <support@uni-im.com>
License: MIT
Project-URL: Homepage, https://github.com/uni-im/uni-agent-sdk
Project-URL: Documentation, https://uni-agent-sdk.readthedocs.io
Project-URL: Repository, https://github.com/uni-im/uni-agent-sdk.git
Project-URL: Issues, https://github.com/uni-im/uni-agent-sdk/issues
Keywords: chatbot,agent,ai,uni-im,messaging
Classifier: Development Status :: 4 - Beta
Classifier: Intended Audience :: Developers
Classifier: License :: OSI Approved :: MIT License
Classifier: Programming Language :: Python :: 3
Classifier: Programming Language :: Python :: 3.8
Classifier: Programming Language :: Python :: 3.9
Classifier: Programming Language :: Python :: 3.10
Classifier: Programming Language :: Python :: 3.11
Classifier: Programming Language :: Python :: 3.12
Classifier: Topic :: Software Development :: Libraries :: Python Modules
Classifier: Topic :: Communications :: Chat
Classifier: Topic :: Scientific/Engineering :: Artificial Intelligence
Requires-Python: >=3.8
Requires-Dist: aiohttp>=3.8.0
Requires-Dist: pydantic>=1.10.0
Requires-Dist: litellm>=1.0.0
Requires-Dist: pika>=1.3.0
Requires-Dist: httpx>=0.24.0
Requires-Dist: tomli>=2.0.0; python_version < "3.11"
Provides-Extra: dev
Requires-Dist: pytest>=7.0.0; extra == "dev"
Requires-Dist: pytest-asyncio>=0.21.0; extra == "dev"
Requires-Dist: black>=22.0.0; extra == "dev"
Requires-Dist: isort>=5.10.0; extra == "dev"
Requires-Dist: flake8>=4.0.0; extra == "dev"
Requires-Dist: mypy>=0.991; extra == "dev"
Provides-Extra: docs
Requires-Dist: sphinx>=5.0.0; extra == "docs"
Requires-Dist: sphinx-rtd-theme>=1.0.0; extra == "docs"
Dynamic: author
Dynamic: home-page
Dynamic: requires-python
